[
    {
        "title": "$:/plugins/GameDungeon/Tiddly2PDF",
        "name": "Tiddly2PDF",
        "author": "GameDungeon",
        "description": "Export Tiddlers as Styled PDFs",
        "plugin-type": "plugin",
        "version": "0.0.1",
        "list": "readme credits",
        "dependents": "",
        "type": "application/json",
        "Modern.TiddlyDev#SHA256-Hashed": "617c369ab3e45cf26704ac2e59a22724f343728f4d8f0351f09590feb97b6601",
        "readme": "! Tiddly2PDF\n\nExport Tiddlers as Styled PDFs",
        "requires-reload": "yes"
    }
]